mcp_windbg/__init__.py
mcp_windbg/__main__.py
mcp_windbg/cdb_session.py
mcp_windbg/server.py
mcp_windbg/prompts/__init__.py
mcp_windbg/prompts/dump-triage.prompt.md
mcp_windbg/tests/test_cdb.py
mcp_windbg/tests/test_remote_debugging.py
mcp_windbg-0.12.2.dist-info/licenses/LICENSE
mcp_windbg-0.12.2.dist-info/METADATA
mcp_windbg-0.12.2.dist-info/WHEEL
mcp_windbg-0.12.2.dist-info/entry_points.txt
mcp_windbg-0.12.2.dist-info/top_level.txt
mcp_windbg-0.12.2.dist-info/RECORD
