Metadata-Version: 2.4
Name: mcp-windbg
Version: 0.12.2
Summary: A Model Context Protocol server providing tools to analyze Windows crash dumps using WinDbg/CDB
Author: svnscha
License-Expression: MIT
Keywords: windbg,cdb,mcp,llm,crash-analysis
Classifier: Development Status :: 4 - Beta
Classifier: Intended Audience :: Developers
Classifier: Programming Language :: Python :: 3
Classifier: Programming Language :: Python :: 3.10
Classifier: Programming Language :: Python :: 3.11
Classifier: Programming Language :: Python :: 3.12
Classifier: Programming Language :: Python :: 3.13
Classifier: Programming Language :: Python :: 3.14
Requires-Python: >=3.10
License-File: LICENSE
Requires-Dist: mcp>=1.17.0
Requires-Dist: pydantic>=2.12.0
Requires-Dist: starlette>=0.40.0
Requires-Dist: uvicorn>=0.30.0
Provides-Extra: test
Requires-Dist: pytest>=8.4.0; extra == "test"
Dynamic: license-file
